aigor/__init__.py
aigor/assistant.py
aigor/common.py
aigor/main.py
aigor/provider.py
aigor/state_manager.py
aigor/providers/__init__.py
aigor/providers/anthropic.py
aigor/providers/identity.py
aigor/providers/openai.py
aigor-0.0.3.dist-info/METADATA
aigor-0.0.3.dist-info/WHEEL
aigor-0.0.3.dist-info/entry_points.txt
aigor-0.0.3.dist-info/top_level.txt
aigor-0.0.3.dist-info/RECORD
