Metadata-Version: 2.1
Name: aigor
Version: 0.0.3
Summary: AIgor is an assistant for oldshol unix users.
Author-email: Igor Morgado <morgado.igor@gmail.com>
Maintainer-email: Igor Morgado <morgado.igor@gmail.com>
Project-URL: Homepage, https://github.com/igormorgado/aigor
Project-URL: Bug Tracker, https://github.com/igormorgado/aigor/issues
Classifier: Programming Language :: Python :: 3
Classifier: License :: OSI Approved :: MIT License
Classifier: Operating System :: OS Independent
Requires-Python: >=3.10
Requires-Dist: python-dotenv
Requires-Dist: colorlog
Requires-Dist: typer
Requires-Dist: anthropic
Requires-Dist: openai
Provides-Extra: dev
Requires-Dist: sphinx; extra == "dev"
Requires-Dist: pytest; extra == "dev"
Requires-Dist: pylint; extra == "dev"
Requires-Dist: mypy; extra == "dev"
Requires-Dist: ipython; extra == "dev"
Requires-Dist: ipdb; extra == "dev"
Requires-Dist: pytest-mypy; extra == "dev"
Requires-Dist: setuptools-scm; extra == "dev"
Requires-Dist: types-PyYAML; extra == "dev"
Requires-Dist: build; extra == "dev"
Requires-Dist: twine; extra == "dev"
Requires-Dist: sphinx-rtd-theme; extra == "dev"
